orm_maker/__app_name__.py
orm_maker/__init__.py
orm_maker/__version__.py
orm_maker/configs.py
orm_maker/configs.yaml
orm_maker/info.py
orm_maker/library.py
orm_maker/make_orm.py
orm_maker/ormm.py
orm_maker/status_result.py
orm_maker-0.1.31.dist-info/METADATA
orm_maker-0.1.31.dist-info/WHEEL
orm_maker-0.1.31.dist-info/entry_points.txt
orm_maker-0.1.31.dist-info/RECORD
