Metadata-Version: 2.3
Name: orm-maker
Version: 0.1.31
Summary: Objection Relation Model Maker for SQLAlchemy
License: GPL-3.0-or-later
Keywords: ORM,orm,object,relational,model,sql,sqlalchemy
Author: dbruce-ae05
Author-email: dbruce.ae05@gmail.com
Requires-Python: >=3.9
Classifier: License :: OSI Approved :: GNU General Public License v3 or later (GPLv3+)
Classifier: Programming Language :: Python :: 3
Classifier: Programming Language :: Python :: 3.9
Classifier: Programming Language :: Python :: 3.10
Classifier: Programming Language :: Python :: 3.11
Classifier: Programming Language :: Python :: 3.12
Classifier: Programming Language :: Python :: 3.13
Requires-Dist: click (>=8.1.8,<9.0.0)
Requires-Dist: pendulum (>=3.0.0,<4.0.0)
Requires-Dist: polars (>=1.27.1,<2.0.0)
Requires-Dist: pyaml (>=25.1.0,<26.0.0)
Requires-Dist: pydantic (>=2.11.3,<3.0.0)
Requires-Dist: sqlalchemy (>=2.0.40,<3.0.0)
Requires-Dist: sqlmodel (>=0.0.24,<0.0.25)
Project-URL: Bug Tracker, https://github.com/dbruce-ae05/orm_maker/issues
Project-URL: Homepage, https://github.com/dbruce-ae05/orm_maker
Project-URL: Repository, https://github.com/dbruce-ae05/orm_maker
